pywap/__init__.py
pywap/client.py
pywap/server.py
pywap-0.0.1.dist-info/METADATA
pywap-0.0.1.dist-info/WHEEL
pywap-0.0.1.dist-info/top_level.txt
pywap-0.0.1.dist-info/RECORD
